{"records":[{"oid":202460254,"typ":"clu","nco":4,"noc":7,"lng":-118.056873,"lat":37.160971,"eag":529,"lag":521,"cxi":1120,"ein":1120,"lin":1120},{"oid":202460255,"typ":"clu","nco":1,"noc":1,"lng":-118.199997,"lat":37.983334,"eag":529,"lag":521,"cxi":1120,"ein":1120,"lin":1120},{"oid":202480253,"typ":"clu","nco":1,"noc":6,"lng":-117.931664,"lat":36.976112,"eag":529,"lag":521,"cxi":1120,"ein":1120,"lin":1120},{"oid":202480255,"typ":"clu","nco":19,"noc":42,"lng":-117.802603,"lat":37.79092,"eag":529,"lag":521,"cxi":1120,"ein":1120,"lin":1120},{"oid":202500254,"typ":"clu","nco":9,"noc":13,"lng":-117.310865,"lat":37.369938,"eag":529,"lag":521,"cxi":1120,"ein":1120,"lin":1120},{"oid":202500255,"typ":"clu","nco":58,"noc":94,"lng":-117.314501,"lat":37.717979,"eag":529,"lag":521,"cxi":1120,"ein":1120,"lin":1120},{"oid":202720240,"typ":"clu","nco":3,"noc":43,"lng":-111.933334,"lat":30.424999,"eag":529,"lag":521,"cxi":1120,"ein":1120,"lin":1120},{"oid":204100265,"typ":"clu","nco":1,"noc":4,"lng":-77.366669,"lat":42.599998,"eag":529,"lag":521,"cxi":1120,"ein":1120,"lin":1120},{"oid":204120259,"typ":"clu","nco":2,"noc":18,"lng":-76.728058,"lat":39.962502,"eag":529,"lag":521,"cxi":1120,"ein":1120,"lin":1120},{"oid":204340263,"typ":"clu","nco":5,"noc":38,"lng":-71.283333,"lat":41.950001,"eag":529,"lag":521,"cxi":1120,"ein":1120,"lin":1120},{"oid":204340264,"typ":"clu","nco":4,"noc":15,"lng":-71.383331,"lat":42.033333,"eag":529,"lag":521,"cxi":1120,"ein":1120,"lin":1120},{"oid":204720271,"typ":"clu","nco":2,"noc":3,"lng":-61.966667,"lat":45.616669,"eag":529,"lag":521,"cxi":1120,"ein":1120,"lin":1120},{"oid":204780271,"typ":"clu","nco":3,"noc":16,"lng":-60.290001,"lat":45.77,"eag":529,"lag":521,"cxi":1120,"ein":1120,"lin":1120},{"oid":204800272,"typ":"clu","nco":4,"noc":38,"lng":-60,"lat":46,"eag":529,"lag":521,"cxi":1120,"ein":1120,"lin":1120},{"oid":204960273,"typ":"clu","nco":3,"noc":23,"lng":-56,"lat":46.916668,"eag":529,"lag":521,"cxi":1120,"ein":1120,"lin":1120},{"oid":204960274,"typ":"clu","nco":30,"noc":97,"lng":-55.946668,"lat":47.026666,"eag":529,"lag":521,"cxi":1120,"ein":1120,"lin":1120},{"oid":205900345,"typ":"clu","nco":1,"noc":5,"lng":-32.5,"lat":82.633331,"eag":529,"lag":521,"cxi":1120,"ein":1120,"lin":1120},{"oid":206520343,"typ":"clu","nco":1,"noc":6,"lng":-16.700001,"lat":81.599998,"eag":529,"lag":521,"cxi":1120,"ein":1120,"lin":1120},{"oid":206700204,"typ":"clu","nco":1,"noc":9,"lng":-12.383333,"lat":12.35,"eag":529,"lag":521,"cxi":1120,"ein":1120,"lin":1120},{"oid":207000259,"typ":"clu","nco":2,"noc":2,"lng":-4.995834,"lat":39.648194,"eag":529,"lag":521,"cxi":1120,"ein":1120,"lin":1120},{"oid":207040256,"typ":"clu","nco":1,"noc":1,"lng":-3.833333,"lat":38.466667,"eag":529,"lag":521,"cxi":1120,"ein":1120,"lin":1120},{"oid":207120285,"typ":"clu","nco":3,"noc":29,"lng":-1.55,"lat":52.566666,"eag":529,"lag":521,"cxi":1120,"ein":1120,"lin":1120},{"oid":207140285,"typ":"clu","nco":1,"noc":2,"lng":-1.46167,"lat":52.52,"eag":529,"lag":521,"cxi":1120,"ein":1120,"lin":1120},{"oid":207700286,"typ":"clu","nco":1,"noc":2,"lng":12.654444,"lat":53.24889,"eag":529,"lag":521,"cxi":1120,"ein":1120,"lin":1120},{"oid":207720289,"typ":"clu","nco":1,"noc":1,"lng":13.1,"lat":54.566666,"eag":529,"lag":521,"cxi":1120,"ein":1120,"lin":1120},{"oid":207740284,"typ":"clu","nco":1,"noc":2,"lng":13.833333,"lat":52.483334,"eag":529,"lag":521,"cxi":1120,"ein":1120,"lin":1120},{"oid":207740291,"typ":"clu","nco":2,"noc":2,"lng":13.983333,"lat":55.716667,"eag":529,"lag":521,"cxi":1120,"ein":1120,"lin":1120},{"oid":207760290,"typ":"clu","nco":1,"noc":1,"lng":14.3,"lat":55.483334,"eag":529,"lag":521,"cxi":1120,"ein":1120,"lin":1120},{"oid":207800290,"typ":"clu","nco":1,"noc":1,"lng":15,"lat":55.166668,"eag":529,"lag":521,"cxi":1120,"ein":1120,"lin":1120},{"oid":207840293,"typ":"clu","nco":1,"noc":1,"lng":16.466667,"lat":56.799999,"eag":529,"lag":521,"cxi":1120,"ein":1120,"lin":1120},{"oid":207840294,"typ":"clu","nco":1,"noc":1,"lng":16,"lat":57.333332,"eag":529,"lag":521,"cxi":1120,"ein":1120,"lin":1120},{"oid":207860293,"typ":"clu","nco":1,"noc":1,"lng":16.566668,"lat":56.799999,"eag":529,"lag":521,"cxi":1120,"ein":1120,"lin":1120},{"oid":207940295,"typ":"clu","nco":1,"noc":1,"lng":18.549999,"lat":57.5,"eag":529,"lag":521,"cxi":1120,"ein":1120,"lin":1120},{"oid":208200316,"typ":"clu","nco":1,"noc":1,"lng":25,"lat":68,"eag":529,"lag":521,"cxi":1120,"ein":1120,"lin":1120},{"oid":208320321,"typ":"clu","nco":1,"noc":5,"lng":28.183332,"lat":70.583336,"eag":529,"lag":521,"cxi":1120,"ein":1120,"lin":1120},{"oid":209240251,"typ":"clu","nco":1,"noc":2,"lng":51.424442,"lat":35.671944,"eag":529,"lag":521,"cxi":1120,"ein":1120,"lin":1120},{"oid":209960267,"typ":"clu","nco":4,"noc":18,"lng":69.420832,"lat":43.599998,"eag":529,"lag":521,"cxi":1120,"ein":1120,"lin":1120},{"oid":209980266,"typ":"clu","nco":5,"noc":43,"lng":69.906668,"lat":43.466667,"eag":529,"lag":521,"cxi":1120,"ein":1120,"lin":1120},{"oid":209980267,"typ":"clu","nco":7,"noc":40,"lng":69.697619,"lat":43.664287,"eag":529,"lag":521,"cxi":1120,"ein":1120,"lin":1120},{"oid":210000266,"typ":"clu","nco":3,"noc":13,"lng":70.216667,"lat":43.366669,"eag":529,"lag":521,"cxi":1120,"ein":1120,"lin":1120},{"oid":210280241,"typ":"clu","nco":1,"noc":3,"lng":77.433334,"lat":30.716667,"eag":529,"lag":521,"cxi":1120,"ein":1120,"lin":1120},{"oid":210320240,"typ":"clu","nco":3,"noc":61,"lng":78.083336,"lat":30.450001,"eag":529,"lag":521,"cxi":1120,"ein":1120,"lin":1120},{"oid":210320241,"typ":"clu","nco":3,"noc":10,"lng":78.166664,"lat":30.5,"eag":529,"lag":521,"cxi":1120,"ein":1120,"lin":1120},{"oid":210360261,"typ":"clu","nco":2,"noc":27,"lng":79.258335,"lat":40.699999,"eag":529,"lag":521,"cxi":1120,"ein":1120,"lin":1120},{"oid":210400266,"typ":"clu","nco":1,"noc":1,"lng":80.416664,"lat":43.083332,"eag":529,"lag":521,"cxi":1120,"ein":1120,"lin":1120},{"oid":210660314,"typ":"clu","nco":4,"noc":62,"lng":86.749168,"lat":67.141113,"eag":529,"lag":521,"cxi":1120,"ein":1120,"lin":1120},{"oid":210680314,"typ":"clu","nco":2,"noc":32,"lng":87.033333,"lat":67.216667,"eag":529,"lag":521,"cxi":1120,"ein":1120,"lin":1120},{"oid":210720292,"typ":"clu","nco":2,"noc":7,"lng":88,"lat":56,"eag":529,"lag":521,"cxi":1120,"ein":1120,"lin":1120},{"oid":211020273,"typ":"clu","nco":3,"noc":7,"lng":95.75,"lat":46.799999,"eag":529,"lag":521,"cxi":1120,"ein":1120,"lin":1120},{"oid":211060273,"typ":"clu","nco":1,"noc":1,"lng":96.51667,"lat":46.700001,"eag":529,"lag":521,"cxi":1120,"ein":1120,"lin":1120},{"oid":211280321,"typ":"clu","nco":7,"noc":48,"lng":102,"lat":70.972221,"eag":529,"lag":521,"cxi":1120,"ein":1120,"lin":1120},{"oid":211280322,"typ":"clu","nco":5,"noc":43,"lng":102,"lat":71,"eag":529,"lag":521,"cxi":1120,"ein":1120,"lin":1120},{"oid":211300229,"typ":"clu","nco":9,"noc":42,"lng":102.800369,"lat":24.689073,"eag":529,"lag":521,"cxi":1120,"ein":1120,"lin":1120},{"oid":211300230,"typ":"clu","nco":2,"noc":11,"lng":102.98333,"lat":25.083332,"eag":529,"lag":521,"cxi":1120,"ein":1120,"lin":1120},{"oid":211300238,"typ":"clu","nco":2,"noc":3,"lng":102.866669,"lat":29.183332,"eag":529,"lag":521,"cxi":1120,"ein":1120,"lin":1120},{"oid":211300272,"typ":"clu","nco":1,"noc":1,"lng":102.76667,"lat":46.25,"eag":529,"lag":521,"cxi":1120,"ein":1120,"lin":1120},{"oid":211300323,"typ":"clu","nco":1,"noc":3,"lng":102.5,"lat":71.5,"eag":529,"lag":521,"cxi":1120,"ein":1120,"lin":1120},{"oid":211320230,"typ":"clu","nco":1,"noc":15,"lng":103.033333,"lat":25.483334,"eag":529,"lag":521,"cxi":1120,"ein":1120,"lin":1120},{"oid":211320231,"typ":"clu","nco":1,"noc":1,"lng":103.066666,"lat":25.633333,"eag":529,"lag":521,"cxi":1120,"ein":1120,"lin":1120},{"oid":211320232,"typ":"clu","nco":15,"noc":62,"lng":103.214444,"lat":26.288888,"eag":529,"lag":521,"cxi":1120,"ein":1120,"lin":1120},{"oid":211320236,"typ":"clu","nco":1,"noc":12,"lng":103.400002,"lat":28.266666,"eag":529,"lag":521,"cxi":1120,"ein":1120,"lin":1120},{"oid":211320239,"typ":"clu","nco":5,"noc":80,"lng":103.399165,"lat":29.523,"eag":529,"lag":521,"cxi":1120,"ein":1120,"lin":1120},{"oid":211320321,"typ":"clu","nco":6,"noc":18,"lng":103.066667,"lat":70.638887,"eag":529,"lag":521,"cxi":1120,"ein":1120,"lin":1120},{"oid":211340232,"typ":"clu","nco":1,"noc":2,"lng":103.5,"lat":26.416668,"eag":529,"lag":521,"cxi":1120,"ein":1120,"lin":1120},{"oid":211340235,"typ":"clu","nco":14,"noc":97,"lng":103.561943,"lat":27.928888,"eag":529,"lag":521,"cxi":1120,"ein":1120,"lin":1120},{"oid":211340318,"typ":"clu","nco":1,"noc":6,"lng":103.849998,"lat":69.01667,"eag":529,"lag":521,"cxi":1120,"ein":1120,"lin":1120},{"oid":211400317,"typ":"clu","nco":2,"noc":16,"lng":105.23333,"lat":68.55,"eag":529,"lag":521,"cxi":1120,"ein":1120,"lin":1120},{"oid":211400323,"typ":"clu","nco":1,"noc":25,"lng":105,"lat":71.5,"eag":529,"lag":521,"cxi":1120,"ein":1120,"lin":1120},{"oid":211420232,"typ":"clu","nco":1,"noc":1,"lng":105.666664,"lat":26.433332,"eag":529,"lag":521,"cxi":1120,"ein":1120,"lin":1120},{"oid":211420233,"typ":"clu","nco":6,"noc":72,"lng":105.847221,"lat":26.630555,"eag":529,"lag":521,"cxi":1120,"ein":1120,"lin":1120},{"oid":211440233,"typ":"clu","nco":1,"noc":8,"lng":106.466667,"lat":26.549999,"eag":529,"lag":521,"cxi":1120,"ein":1120,"lin":1120},{"oid":211440236,"typ":"clu","nco":1,"noc":9,"lng":106.300003,"lat":28.266666,"eag":529,"lag":521,"cxi":1120,"ein":1120,"lin":1120},{"oid":211440245,"typ":"clu","nco":4,"noc":44,"lng":106.25,"lat":32.966667,"eag":529,"lag":521,"cxi":1120,"ein":1120,"lin":1120},{"oid":211460234,"typ":"clu","nco":1,"noc":1,"lng":106.949997,"lat":27.049999,"eag":529,"lag":521,"cxi":1120,"ein":1120,"lin":1120},{"oid":211460244,"typ":"clu","nco":1,"noc":39,"lng":106.816666,"lat":32.349998,"eag":529,"lag":521,"cxi":1120,"ein":1120,"lin":1120},{"oid":211480323,"typ":"clu","nco":2,"noc":47,"lng":107,"lat":71.833336,"eag":529,"lag":521,"cxi":1120,"ein":1120,"lin":1120},{"oid":211520233,"typ":"clu","nco":1,"noc":1,"lng":108.416664,"lat":26.766666,"eag":529,"lag":521,"cxi":1120,"ein":1120,"lin":1120},{"oid":211520244,"typ":"clu","nco":1,"noc":6,"lng":108,"lat":32,"eag":529,"lag":521,"cxi":1120,"ein":1120,"lin":1120},{"oid":211520298,"typ":"clu","nco":1,"noc":4,"lng":108.449997,"lat":59.333332,"eag":529,"lag":521,"cxi":1120,"ein":1120,"lin":1120},{"oid":211560296,"typ":"clu","nco":1,"noc":2,"lng":109,"lat":58,"eag":529,"lag":521,"cxi":1120,"ein":1120,"lin":1120},{"oid":211640241,"typ":"clu","nco":17,"noc":257,"lng":111.149999,"lat":30.768627,"eag":529,"lag":521,"cxi":1120,"ein":1120,"lin":1120},{"oid":211680312,"typ":"clu","nco":4,"noc":111,"lng":112.283333,"lat":66.400002,"eag":529,"lag":521,"cxi":1120,"ein":1120,"lin":1120},{"oid":211700303,"typ":"clu","nco":1,"noc":2,"lng":112.666664,"lat":61.666668,"eag":529,"lag":521,"cxi":1120,"ein":1120,"lin":1120},{"oid":211880240,"typ":"clu","nco":2,"noc":2,"lng":117,"lat":30.083332,"eag":529,"lag":521,"cxi":1120,"ein":1120,"lin":1120},{"oid":211900243,"typ":"clu","nco":1,"noc":15,"lng":117.866669,"lat":31.6,"eag":529,"lag":521,"cxi":1120,"ein":1120,"lin":1120},{"oid":211920239,"typ":"clu","nco":1,"noc":14,"lng":118.083336,"lat":29.916668,"eag":529,"lag":521,"cxi":1120,"ein":1120,"lin":1120},{"oid":211940237,"typ":"clu","nco":2,"noc":15,"lng":118.616669,"lat":28.733334,"eag":529,"lag":521,"cxi":1120,"ein":1120,"lin":1120},{"oid":212040237,"typ":"clu","nco":8,"noc":16,"lng":121.422501,"lat":28.941111,"eag":529,"lag":521,"cxi":1120,"ein":1120,"lin":1120},{"oid":212120306,"typ":"clu","nco":2,"noc":2,"lng":123,"lat":63,"eag":529,"lag":521,"cxi":1120,"ein":1120,"lin":1120},{"oid":212140322,"typ":"clu","nco":1,"noc":52,"lng":123.966667,"lat":71.333336,"eag":529,"lag":521,"cxi":1120,"ein":1120,"lin":1120},{"oid":212180301,"typ":"clu","nco":3,"noc":72,"lng":124.716667,"lat":60.700001,"eag":529,"lag":521,"cxi":1120,"ein":1120,"lin":1120},{"oid":212180324,"typ":"clu","nco":3,"noc":5,"lng":124.587502,"lat":72.090279,"eag":529,"lag":521,"cxi":1120,"ein":1120,"lin":1120},{"oid":212200301,"typ":"clu","nco":17,"noc":190,"lng":125.29608,"lat":60.82843,"eag":529,"lag":521,"cxi":1120,"ein":1120,"lin":1120},{"oid":212220301,"typ":"clu","nco":3,"noc":64,"lng":125.76667,"lat":60.916668,"eag":529,"lag":521,"cxi":1120,"ein":1120,"lin":1120},{"oid":212240302,"typ":"clu","nco":1,"noc":1,"lng":126,"lat":61,"eag":529,"lag":521,"cxi":1120,"ein":1120,"lin":1120},{"oid":212280297,"typ":"clu","nco":3,"noc":47,"lng":127,"lat":58.75,"eag":529,"lag":521,"cxi":1120,"ein":1120,"lin":1120},{"oid":212280322,"typ":"clu","nco":2,"noc":68,"lng":127.458332,"lat":71.05,"eag":529,"lag":521,"cxi":1120,"ein":1120,"lin":1120},{"oid":212280323,"typ":"clu","nco":2,"noc":42,"lng":127.366669,"lat":71.541668,"eag":529,"lag":521,"cxi":1120,"ein":1120,"lin":1120},{"oid":212300322,"typ":"clu","nco":1,"noc":8,"lng":127.650002,"lat":71,"eag":529,"lag":521,"cxi":1120,"ein":1120,"lin":1120},{"oid":212320297,"typ":"clu","nco":2,"noc":63,"lng":128,"lat":58.75,"eag":529,"lag":521,"cxi":1120,"ein":1120,"lin":1120},{"oid":212380297,"typ":"clu","nco":2,"noc":15,"lng":129.5,"lat":58.5,"eag":529,"lag":521,"cxi":1120,"ein":1120,"lin":1120},{"oid":212380304,"typ":"clu","nco":3,"noc":24,"lng":129.666672,"lat":62,"eag":529,"lag":521,"cxi":1120,"ein":1120,"lin":1120},{"oid":212420297,"typ":"clu","nco":2,"noc":12,"lng":130.616669,"lat":58.75,"eag":529,"lag":521,"cxi":1120,"ein":1120,"lin":1120},{"oid":212440294,"typ":"clu","nco":5,"noc":89,"lng":131.199997,"lat":57.289999,"eag":529,"lag":521,"cxi":1120,"ein":1120,"lin":1120},{"oid":212460295,"typ":"clu","nco":3,"noc":21,"lng":131.833328,"lat":57.666668,"eag":529,"lag":521,"cxi":1120,"ein":1120,"lin":1120},{"oid":212480294,"typ":"clu","nco":1,"noc":17,"lng":132,"lat":57.166668,"eag":529,"lag":521,"cxi":1120,"ein":1120,"lin":1120},{"oid":212600303,"typ":"clu","nco":2,"noc":19,"lng":135.483337,"lat":61.866669,"eag":529,"lag":521,"cxi":1120,"ein":1120,"lin":1120}]}