{"type":"Topology","objects":{"Kasimovian":{"type":"GeometryCollection","geometries":[{"type":"Polygon","arcs":[[0,1]]},{"type":"Polygon","arcs":[[2]]},{"type":"Polygon","arcs":[[3]]},{"type":"Polygon","arcs":[[4]]},{"type":"Polygon","arcs":[[5]]},{"type":"Polygon","arcs":[[6]]},{"type":"Polygon","arcs":[[7]]},{"type":"Polygon","arcs":[[8]]},{"type":"Polygon","arcs":[[9]]},{"type":"Polygon","arcs":[[10,11,12,13]]},{"type":"Polygon","arcs":[[14,15,16,17,18,19]]},{"type":"Polygon","arcs":[[20]]},{"type":"Polygon","arcs":[[21,-18,22,23,24]]},{"type":"Polygon","arcs":[[25]]},{"type":"Polygon","arcs":[[26]]},{"type":"Polygon","arcs":[[27]]},{"type":"Polygon","arcs":[[28,29]]},{"type":"Polygon","arcs":[[30,31,-12,32,33]]},{"type":"Polygon","arcs":[[34]]},{"type":"MultiPolygon","arcs":[[[35,36,37,38,39,40,41],[42]],[[43,44]],[[45,46]]]},{"type":"Polygon","arcs":[[-29,47]]},{"type":"Polygon","arcs":[[48]]},{"type":"Polygon","arcs":[[49]]},{"type":"Polygon","arcs":[[50,51]]},{"type":"Polygon","arcs":[[52]]},{"type":"Polygon","arcs":[[-51,53]]},{"type":"Polygon","arcs":[[54]]},{"type":"Polygon","arcs":[[55]]},{"type":"Polygon","arcs":[[-40,56,57]]},{"type":"Polygon","arcs":[[58]]},{"type":"Polygon","arcs":[[59]]},{"type":"Polygon","arcs":[[60,61,62,63,64,65,-20,66,67,68,69,70]]},{"type":"Polygon","arcs":[[71]]},{"type":"Polygon","arcs":[[-65,72,-16,73]]},{"type":"Polygon","arcs":[[-24,74]]},{"type":"Polygon","arcs":[[75]]},{"type":"Polygon","arcs":[[76]]},{"type":"Polygon","arcs":[[77]]},{"type":"Polygon","arcs":[[78]]},{"type":"Polygon","arcs":[[79]]},{"type":"Polygon","arcs":[[-70,80,-68,81,82]]},{"type":"Polygon","arcs":[[83]]},{"type":"Polygon","arcs":[[84,85]]},{"type":"MultiPolygon","arcs":[[[86,-1,87]],[[88]]]},{"type":"Polygon","arcs":[[89]]},{"type":"Polygon","arcs":[[-85,90]]},{"type":"Polygon","arcs":[[91]]},{"type":"Polygon","arcs":[[-61,92,-63,93]]},{"type":"Polygon","arcs":[[94]]},{"type":"Polygon","arcs":[[95]]},{"type":"Polygon","arcs":[[96]]},{"type":"Polygon","arcs":[[97]]},{"type":"Polygon","arcs":[[98]]},{"type":"Polygon","arcs":[[99]]},{"type":"Polygon","arcs":[[100]]},{"type":"Polygon","arcs":[[101]]},{"type":"Polygon","arcs":[[102]]},{"type":"Polygon","arcs":[[103]]},{"type":"Polygon","arcs":[[104]]},{"type":"Polygon","arcs":[[-14,105,-31,106,107]]},{"type":"Polygon","arcs":[[108]]},{"type":"Polygon","arcs":[[109]]}]}},"arcs":[[[8616,3138],[-32,-112],[-40,-52],[-130,-71],[-41,-44],[-65,-45],[-16,-26],[-54,-20],[-58,-58],[-26,3],[-22,29],[-10,-11]],[[8122,2731],[-3,49],[-44,68],[-51,55],[40,24],[113,-11],[93,31],[23,-2],[119,46],[26,13],[48,71],[76,51],[54,12]],[[5092,1588],[-21,-14],[-31,255],[-21,75],[87,180],[25,38],[121,121],[106,22],[17,41],[42,19],[231,-27],[-85,-196],[-59,-92],[-16,-89],[-86,-114],[-31,-37],[-75,-58],[-58,-108],[-135,-9],[-11,-7]],[[7638,7076],[61,19],[-37,-69],[-13,-67],[-50,-121],[-132,-138],[-39,-81],[-45,25],[-23,39],[-30,11],[-45,-16],[-7,-18],[-11,30],[-29,20],[18,171],[-39,-50],[-14,1],[14,-1],[42,56],[99,75],[50,87],[81,20],[149,7]],[[8679,3492],[-47,52],[33,6],[58,29],[89,7],[100,-58],[140,-66],[153,-110],[124,-145],[13,-30],[24,-28],[99,2],[-44,-90],[14,-1],[21,-25],[3,-17],[26,-11],[-75,14],[-16,-13],[0,-8],[-14,-3],[-43,22],[-11,28],[4,3],[-2,40],[-5,15],[-119,101],[-140,102],[-144,39],[-106,-10],[-3,17],[-56,90],[-28,28],[-48,20]],[[8679,3492],[-194,-35],[-39,38],[-42,57],[-24,64],[0,65],[10,14],[44,23],[112,-34],[2,-35],[11,-47],[42,-11],[23,-40],[55,-59]],[[5447,4800],[-74,-198],[-106,-319],[-11,-298],[-19,-120],[1,-90],[-10,-52],[-2,-106],[-8,-39],[-18,-50],[-29,-41],[-96,-97],[-34,-15],[-279,90],[-21,82],[-38,71],[-36,44],[-45,36],[-60,32],[-9,16],[-49,43],[-11,28],[23,9],[8,13],[-71,185],[-62,96],[-6,45],[26,185],[4,95],[-5,69],[15,67],[-10,79],[-19,42],[-4,47],[2,41],[7,16],[33,14],[24,38],[12,41],[22,19],[12,25],[16,-61],[14,8],[24,35],[22,37],[11,33],[3,34],[18,21],[16,46],[8,40],[-1,40],[8,23],[24,32],[42,38],[84,31],[58,-12],[26,35],[39,9],[43,-39],[35,-59],[110,-95],[77,-137],[273,-129],[14,30],[17,-20],[-38,-83]],[[8240,3700],[70,120],[27,188],[60,19],[-50,201],[-3,45],[22,38],[47,23],[48,-25],[42,13],[19,-295],[-9,0],[-96,-184],[-95,-261],[-74,-77],[-8,195]],[[7131,2445],[49,14],[75,67],[84,44],[70,26],[80,12],[50,-5],[55,-39],[73,-74],[27,-47],[-93,46],[-85,-3],[-40,-96],[-211,-123],[-92,-17],[-75,2],[-138,58],[-166,218],[-25,11],[-33,41],[-15,42],[44,-20],[166,-117],[109,-37],[91,-3]],[[5504,1607],[19,-35],[32,-15],[-12,-83],[-37,-84],[-44,-35],[-23,-66],[11,-74],[-239,-237],[-100,-28],[-70,-4],[-267,66],[-105,-26],[-157,19],[-119,-2],[-208,-55],[-116,2],[-93,17],[-27,19],[-17,56],[-36,32],[-171,10],[-129,27],[-74,42],[-45,53],[-128,85],[-132,152],[-87,209],[-59,192],[78,64],[67,35],[45,46],[155,92],[38,45],[43,34],[85,16],[61,43],[66,2],[156,113],[88,94],[-12,94],[8,14],[17,-1],[31,-46],[147,73],[69,14],[52,-27],[46,59],[29,64],[-2,31],[18,40],[60,59],[89,127],[16,164],[68,95],[48,34],[30,4],[77,52],[17,49],[1,50],[-22,194],[268,-147],[-35,15],[7,-68],[21,-79],[65,-147],[155,-141],[58,-38],[77,-21],[20,-23],[25,-52],[85,-389],[11,-183],[-37,8],[-43,-18],[-17,-41],[-107,-18],[-124,-119],[-26,-36],[-91,-179],[20,-75],[24,-256],[33,21],[136,5],[61,106],[78,56],[55,58],[50,-58],[-13,-102],[8,-43]],[[6226,2216],[-19,12],[-42,117],[-35,47],[-18,14],[-32,102],[-7,51],[42,19],[25,-12],[33,39],[21,-26],[17,-5]],[[6211,2574],[45,-127],[88,-152]],[[6344,2295],[-105,-54]],[[6239,2241],[-13,-25]],[[5642,6321],[53,-56],[-16,9]],[[5679,6274],[-69,-38],[-54,-63],[-27,-64],[-38,-158],[-31,-45],[-34,-5],[-39,20],[-10,22],[-27,20],[-119,-88]],[[5231,5875],[-53,-61],[-10,15],[-4,23],[-2,117],[-14,80],[30,-6]],[[5178,6043],[23,24],[83,174],[26,47]],[[5310,6288],[22,20],[15,79]],[[5347,6387],[35,-27],[102,-21],[28,25],[38,-3],[18,-20],[24,6],[50,-26]],[[7223,6887],[-18,-101],[-40,-60],[-64,-59],[-44,-15],[-49,5],[-54,28],[-41,43],[-51,141],[5,72],[-9,87],[-30,117],[-55,110],[-22,60],[2,139],[-16,114],[-58,160],[-61,196],[-6,103],[0,140],[24,-21],[59,-105],[121,-153],[47,-36],[81,-23],[82,-131],[40,-41],[75,-11],[61,-22],[196,36],[-92,-338],[6,-66],[-14,-37],[-16,-138],[-59,-194]],[[5347,6387],[-14,-79],[-23,-20]],[[5178,6043],[-31,7],[-8,111],[20,44],[51,52]],[[5210,6257],[44,104]],[[5254,6361],[104,468],[-11,-442]],[[1620,797],[17,-20],[-33,-30],[28,-25],[112,-7],[20,-10],[-5,-13],[-21,-15],[-67,-25],[-66,-10],[-85,4],[-34,19],[-56,61],[-128,35],[-51,57],[-121,-124],[-339,-113],[-249,-4],[-152,24],[-253,535],[88,-7],[107,27],[293,165],[64,26],[30,1],[116,76],[25,63],[69,-15],[200,47],[192,31],[400,21],[199,40],[8,-202],[-98,-166],[128,-64],[19,-61],[73,-45],[5,-13],[-22,-14],[-23,4],[-111,46],[-8,-5],[18,-15],[-18,0],[57,-30],[16,-22],[-30,-16],[-60,20],[-19,25],[-24,-3],[20,-49],[15,-4],[11,-30],[12,0],[2,19],[50,-4],[43,-32],[-13,-16],[-222,-88],[-12,-12],[25,-19],[-1,-9],[-69,5],[-72,-14]],[[8841,6873],[-27,-4],[-12,-18],[-9,-34],[-49,-31],[-5,-16],[-4,-64],[3,-73],[-49,-15],[-71,-87],[-23,-14],[-58,-64],[-45,71],[-35,20],[-44,74],[-36,147],[-63,160],[-93,193],[-51,298],[-72,353],[5,19],[154,-166],[168,-163],[47,-75],[50,-49],[112,-165],[123,-89],[63,-122],[21,-86]],[[8919,4919],[37,7],[292,-211],[-19,-203],[-150,-228],[-70,-13],[-101,42],[-63,59],[-37,54],[-60,140],[-62,56],[23,50],[210,247]],[[6594,3213],[-63,19],[-19,21],[-8,36]],[[6504,3289],[-16,16],[8,70],[-63,89],[-34,86],[-9,93],[1,237],[45,5],[34,23],[38,1],[40,-28],[19,-33],[3,-26],[19,-159],[8,-338],[12,-47],[13,-19],[-8,-26],[-20,-20]],[[6685,2368],[-251,-34],[-5,12]],[[6429,2346],[-85,-51]],[[6211,2574],[9,28],[24,38],[193,153],[76,109],[-7,-102],[43,-125],[138,-235],[125,-85]],[[6812,2355],[-50,3],[-77,10]],[[7965,2588],[0,42],[79,-3],[42,9],[53,33],[82,205],[24,130],[49,127],[74,13],[15,46],[25,-78],[-38,-52],[-39,-187],[38,-248],[-69,-90],[-61,-8],[-35,-25],[-238,-32],[-1,118]],[[132,1244],[-86,54],[143,-296],[440,-207],[-92,195]],[[537,990],[516,-324]],[[1053,666],[293,104],[117,123],[43,-58],[114,-38]],[[1620,797],[45,-61],[28,-20],[76,-7],[61,9],[65,23],[28,27],[-18,11],[-101,10],[-23,25],[33,29],[-13,21],[67,12],[64,-7],[2,9],[-21,20],[195,82]],[[2108,980],[12,-44],[-27,-70],[24,2],[45,36],[34,0],[51,-41],[-23,-44],[26,-48],[-36,-31],[-2,-20]],[[2212,720],[739,632]],[[2951,1352],[79,-9],[87,4],[118,-62],[97,-22],[260,-98],[45,2],[80,33],[66,45],[100,-1],[62,10],[130,-24],[100,28],[87,-73],[79,-17],[37,5],[37,-15],[72,16],[73,-11],[82,6],[97,-60],[78,-31],[52,-8],[109,8],[71,24],[111,166],[71,82],[38,27],[134,-53],[8,-18],[-20,-57],[-40,-49],[20,-30],[59,-18],[73,11],[241,113],[173,41],[202,-13],[122,17],[186,-28],[343,9],[73,-28],[96,-4],[86,18],[72,-36],[66,-4],[147,33],[113,49],[59,41],[-22,74],[197,42],[35,-50],[62,-44],[91,21],[108,3],[320,83],[194,24],[101,33],[97,54],[125,50],[91,25],[86,-7],[191,-68],[164,-43],[42,-3],[49,-66],[61,-34],[85,-8],[179,-40],[56,-24],[78,-66],[41,7],[17,-26],[36,-30],[30,0],[-9996,18],[46,2],[50,-13],[36,-41]],[[1053,666],[-14,-6],[-118,-2],[570,-267],[-438,275]],[[537,990],[-348,218]],[[189,1208],[243,5],[105,-223]],[[132,1244],[57,-36]],[[189,1208],[-25,0],[-32,36]],[[6594,3213],[11,-59],[-13,-32],[-1,-65],[31,-6],[65,16],[-97,-162],[-32,-105],[-97,-172],[-208,-119],[-132,-32],[-185,0],[8,-16],[-36,0],[-43,23],[-1,39],[-13,75],[7,102],[-41,382],[19,134],[0,45],[-10,51],[-4,294],[79,177],[44,152],[9,55],[14,33],[14,67],[11,19],[71,36],[37,7],[8,-8],[21,18],[62,-108],[-7,-21],[15,-106],[11,-53],[16,-41],[24,-123],[53,-60],[25,-45],[54,-161],[81,-121],[40,-34]],[[2449,1788],[-52,-135],[-45,-96],[-51,-71],[-61,-59],[-54,-39],[-82,-38],[-98,7],[-88,38],[-26,-9],[-115,58],[74,171],[-18,201],[15,15],[72,21],[101,123],[92,88],[75,101],[230,148],[67,-30],[4,-6],[-5,-6],[45,-41],[15,-36],[6,-50],[4,-3],[-16,-80],[-25,-22],[-14,-97],[-43,-83],[-7,-70]],[[3795,5578],[2,-35],[23,-74],[15,-23],[6,-38],[-57,-173],[-41,-199],[-8,-42],[0,-149],[-35,-38],[-32,-2],[-21,70],[-12,83],[-26,256],[-7,146],[10,83],[3,-3],[16,50],[30,33],[9,43],[22,55],[6,123],[7,12],[6,78],[20,56],[18,122],[-2,53],[17,65],[14,96],[-4,10],[17,60],[17,-79],[-18,-159],[4,-263],[-4,-127],[5,-90]],[[5167,5921],[-12,-2],[-52,-60],[-20,-47],[-79,-92],[-92,1],[-25,-17],[-101,-129],[-69,-186]],[[4717,5389],[-31,3],[-79,-51],[-99,-141],[-90,-72],[-38,-9],[-94,18],[-86,65],[-44,58],[-18,10],[-167,-18],[-8,-26],[-14,-97],[-12,32],[-18,9],[-33,51],[-7,31],[-18,80],[-15,122],[-42,245],[-7,163],[-28,61],[4,72],[7,17],[7,80],[-17,149],[22,46],[18,107],[19,216],[-13,48],[5,34],[33,23],[60,-152],[31,-57],[40,-46],[22,-1],[14,-20],[27,-5],[14,-27],[5,-110],[14,-22],[0,-36],[5,221],[32,262],[0,206],[7,282],[31,226],[49,221],[44,480],[5,11],[1,42],[9,-24],[16,-7],[11,-22],[18,9],[75,-1],[18,-26],[51,24],[1,-59],[60,-26],[81,51],[61,75],[45,-24],[-25,-28],[-15,-32],[6,-145],[-7,-90],[75,-125],[173,-230],[24,65],[18,-88],[-11,-80],[33,-124],[23,-50],[19,-193],[25,-80],[-21,-302],[-20,-27],[8,-96],[45,-251],[35,-89],[7,0],[30,-84],[39,-137],[5,-53]],[[5155,1172],[17,25],[32,13],[71,-7],[25,-13],[73,-3],[47,-19],[83,-6],[19,-19],[2,-18],[-7,-11],[-61,-26],[-69,-16],[-150,-10],[-37,9],[-46,35],[-5,39],[6,27]],[[5167,5921],[13,-137],[14,-38],[35,-14],[8,-29],[0,-73],[-34,-104],[-7,-93],[-10,-50],[-38,29],[-44,87],[-9,36],[-35,-1],[-89,-82],[-84,-24],[-30,-36],[-35,-66],[-27,-20],[-52,10],[-45,-26],[19,99]],[[6346,4350],[-1,-118],[18,-69],[43,-59],[-38,-223],[-8,-94],[16,-103],[41,-123],[-20,-60],[-18,32],[-52,165],[-21,185],[-15,59],[-39,90],[-3,132],[-8,48],[-2,57],[1,111],[8,16],[-59,204],[-2,29],[-13,42],[37,-58],[52,-36],[32,-43],[41,-95],[10,-89]],[[8788,6461],[77,-63],[68,-235],[24,-154],[-7,-81],[-12,-64],[33,-58],[40,-112],[-41,-344],[23,-376],[-229,-120],[-44,-55],[-64,-13],[-77,13],[-45,83],[-50,51],[-32,18],[-54,-5],[57,93],[28,74],[20,64],[26,174],[12,45],[52,145],[81,197],[59,94],[28,106],[5,82],[25,111],[-33,125],[-9,50],[-46,151],[-13,110],[14,8],[84,-114]],[[2108,980],[33,10],[14,15],[-38,35],[-47,5],[-3,-19],[-11,0],[-8,31],[-14,4],[-15,50],[22,2],[17,-26],[55,-22],[30,15],[-14,23],[-51,31],[16,0],[-15,16],[7,5],[102,-50],[22,-5],[22,13],[-4,14],[-66,47],[-15,61],[31,7],[93,-47],[109,-15],[98,31],[66,36],[74,55],[64,67],[57,94],[65,132],[4,-98],[26,-65],[61,-62],[56,-18]],[[2951,1352],[-414,-384],[-325,-248]],[[6087,1989],[13,-8],[-10,-17],[16,-26],[-15,-18],[7,-15],[-19,-66],[-24,-35],[6,-35],[-73,-78],[-26,-1],[-137,-117],[-48,-18],[-20,-24],[-198,-115],[-12,-17],[-42,-17],[-32,-1],[-56,32],[-51,-3],[-32,38],[2,57],[29,79],[58,55],[23,60],[47,30],[85,18],[13,25],[19,10],[19,48],[10,68],[12,35],[16,20],[75,17],[30,-12],[36,-41],[56,-6],[92,21],[9,23],[47,25],[33,36],[31,-7],[11,-20]],[[4717,5284],[-20,-16],[-30,-59],[-52,-148],[-118,-96],[-34,-64],[-52,-259],[-22,-48],[-20,-13],[-66,55],[2,95],[11,88],[-4,148],[-13,53],[-21,28],[-51,210],[75,-68],[93,-30],[38,3],[92,59],[103,126],[80,39],[30,-7],[-21,-96]],[[6174,6353],[-19,-29],[-38,-10],[2,-9]],[[6119,6305],[-62,-15]],[[6057,6290],[-43,-141],[-98,-83]],[[5916,6066],[-69,35],[-14,52],[-58,71]],[[5775,6224],[-79,39]],[[5696,6263],[-54,58]],[[5347,6387],[12,502],[-7,69],[3,59],[38,188],[31,112],[2,95],[-14,129],[19,7],[78,105]],[[5509,7653],[41,96],[10,95]],[[5560,7844],[-14,130],[-36,162]],[[5510,8136],[0,50],[15,69],[14,28],[21,27]],[[5560,8310],[23,12],[23,-23],[24,-173],[18,-72],[16,-52],[26,-39],[22,-2],[86,99],[24,17],[44,7],[27,-30],[59,-238],[92,-137],[83,-105],[34,-94],[22,-131],[53,-118],[30,-99],[-1,-97],[-46,-161],[-19,-97],[-14,-354],[-12,-70]],[[3951,6391],[-22,-3],[-41,39],[-33,51],[-65,141],[-32,-28],[-39,-4],[4,40],[71,185],[16,23],[34,78],[20,76],[7,75],[13,-75],[24,-43],[15,-3],[29,18],[-5,-53],[2,-75],[-14,-69],[6,-70],[24,-71],[-25,-56],[-18,-92],[6,-55],[23,-29]],[[5775,6224],[50,-62],[-43,-7],[-30,21],[-2,-11],[-38,-10],[-45,-80],[-6,-69],[-4,12],[-102,-143],[-12,-61],[-26,-35],[-3,-30],[-8,-28],[2,-51],[8,-16],[13,5],[12,-31],[-38,-52],[-9,-46],[6,-43],[-9,-17],[-37,50],[-21,-16],[-26,7],[-26,-7],[-65,38],[-31,32],[28,17],[1,41],[-34,77],[-19,19],[0,13],[-82,74],[52,60]],[[5679,6274],[17,-11]],[[5210,6257],[-52,-53],[24,62],[8,43],[-6,84],[3,41],[22,41],[20,64],[28,42],[24,67],[69,140],[-16,-72],[-80,-355]],[[5967,4026],[-37,-165],[-70,-191],[-23,117],[6,105],[17,77],[11,-12],[55,2],[26,54],[21,64],[-6,-51]],[[3072,1769],[14,-19],[47,-17],[44,-198],[161,-210],[241,-212],[-93,-30],[-162,-10],[-119,43],[-58,40],[-1,12],[-145,99],[-93,31],[-71,69],[-118,134],[-70,134],[-70,84],[-38,35],[-68,5],[-32,21],[-9,56],[-2,-29],[-3,52],[6,140],[40,101],[62,107],[96,121],[153,137],[23,49],[131,144],[115,164],[84,86],[39,19],[23,30],[77,150],[111,182],[43,103],[67,-235],[79,-185],[-120,-240],[-31,-79],[-160,-273],[-6,-25],[37,-78],[209,-270],[-70,2],[-216,-49],[-56,-50],[-91,-141]],[[3834,7312],[136,-387],[46,-251],[46,-153],[-17,-2],[-34,80],[-18,1],[-23,-34],[-42,-8],[-19,37],[-7,101],[7,78],[-37,28],[-23,49],[-6,75],[-20,60],[-17,94],[-63,164],[-62,115],[2,15],[-12,134],[-23,212],[-41,230],[20,-30],[33,-123],[8,-68],[19,-46],[29,-42],[37,-91],[18,-103],[63,-135]],[[5672,8355],[-40,204],[-5,155],[4,119],[142,-45],[13,18],[4,88],[26,97],[18,95],[4,41],[-2,50],[-13,40],[-139,144],[-35,68],[-189,130],[-21,-3],[28,95],[0,89],[119,66],[281,108],[177,82],[58,3],[48,-15],[172,-116],[96,-126],[46,-24],[52,-49],[249,3],[93,-118],[60,-60],[56,-24],[200,-334],[37,-124],[14,-97],[6,-157],[-23,-116],[-64,-126],[-90,-201],[-56,-73],[-62,-103],[-45,-30],[-110,-29],[-66,-101],[-46,-44],[-139,-68],[-76,-10],[-24,-18],[-9,12],[-30,6],[-37,-40],[-18,-34],[-57,-157],[-19,-15],[-30,17],[-24,36],[-29,53],[-54,142],[-9,2],[-18,38],[-28,20],[-95,20],[-64,26],[-6,84],[6,126],[-7,46],[7,91],[-17,151],[-38,32],[-71,-78],[-47,1],[-32,-53],[-32,-10]],[[5199,7755],[-45,-43],[-124,-175],[-59,-156],[-3,40],[-30,-51],[-140,307],[-58,157],[18,84],[13,144],[19,23],[54,18],[85,-131],[9,65],[26,-34],[96,-67],[184,-73],[0,-74],[-45,-34]],[[5510,8136],[37,-162],[13,-130]],[[5509,7653],[-77,-105],[-18,-6],[-21,81],[-135,341]],[[5258,7964],[21,55],[42,65],[5,68],[25,73],[-2,42],[4,28],[24,91],[32,-1],[174,-64],[-23,-11]],[[5534,4238],[6,-10],[10,1],[19,62],[7,11],[21,1],[-4,-16],[29,-6],[37,-31],[21,-68],[89,-173],[21,-21],[55,-6],[23,-29],[-13,-67],[-2,-106],[27,-114],[31,-288],[13,-47],[5,-44],[-4,-138],[23,-102],[-26,-199],[-1,-174],[-10,2],[-2,-31],[-14,-8],[-9,-145],[-19,-34],[-1,-19],[-92,-59],[-72,-142],[-43,51],[-195,21],[-13,184],[-88,387],[-24,51],[-21,23],[-77,20],[-58,36],[-155,138],[-66,147],[-22,78],[-7,68],[35,-15],[34,9],[100,78],[31,35],[20,46],[10,37],[8,106],[12,49],[4,90],[25,116],[24,294],[119,298],[82,182],[41,76],[4,-6],[1,-71],[-8,-108],[8,-31],[-17,-38],[-9,-1],[-5,-12],[4,-50],[78,-288]],[[5689,4168],[8,79],[8,3],[10,-14],[10,21],[-3,42],[12,75],[8,10],[16,60],[32,156],[6,243],[-7,10],[-4,26],[13,12],[7,-8],[3,25],[6,10],[18,-18],[4,-15],[9,25]],[[5845,4910],[32,0],[45,-85],[13,-83],[5,-2],[-2,-74],[13,-93],[4,21],[-6,-43],[-19,-44],[1,-163],[-27,-44],[-24,2],[-12,-20],[-8,8],[4,-9],[-12,-58],[8,-47],[-7,-3],[-1,-10],[-17,45],[-71,90],[-48,-185],[-23,10],[-4,45]],[[0,1171],[9568,53],[-108,35],[-72,11],[-25,14],[-175,-13],[-274,-50],[-141,33],[-257,-47],[-120,-47],[-202,-17],[-201,-36],[-151,12],[-48,19],[-20,27],[-39,-11],[-54,54],[-55,35],[-12,18],[40,45],[-13,16],[-61,-21],[-92,28],[-73,-5],[-16,46],[34,88],[59,44],[85,-97],[32,26],[13,-1],[-1,9],[9,-18],[13,7],[29,-9],[95,57],[4,44],[-17,52],[-106,130],[15,34],[-65,78],[17,26],[-19,64],[-27,22],[-23,-19],[-6,21],[-82,115],[22,32],[3,17],[32,35],[49,1],[41,-54],[-2,-29],[-22,-21],[7,-16],[-9,-22],[8,-8],[54,52],[33,-2],[91,111],[-86,97],[-6,68],[75,35],[-4,14],[50,26],[-13,48],[22,14],[-15,61],[2,67],[24,-13],[19,9],[27,-43],[31,-14],[5,-22],[36,-13],[23,10],[8,-26],[17,8],[32,-21],[40,29],[-5,12],[11,8],[0,23],[12,10],[-7,19],[11,20],[-4,15],[17,12],[1,33],[13,39],[18,25],[3,42]],[[8616,3138],[7,52],[-4,51],[-14,27],[104,50],[106,14],[62,-1],[249,-101],[14,-51],[-74,-85],[8,-32],[-9,-35],[3,-12],[7,7],[1,-13],[-10,-69],[7,-39],[25,-40],[17,7],[60,90],[51,-33],[31,-6],[148,19],[54,-54],[26,-67],[45,-48],[21,-53],[47,-63],[40,-77],[11,-28],[-22,-75],[1,-17],[34,-26],[15,-29],[11,-52],[57,-55],[6,-38],[29,-64],[2,-73],[42,-75],[14,-66],[5,-129],[20,-90],[74,-113],[6,-33],[-10,-41],[-26,-6],[-11,-17],[41,-11],[9,-17],[26,-13],[27,-26],[-9999,-311]],[[0,1171],[0,311],[107,-95],[77,-112],[5,-38],[-70,-54],[-43,-13],[-76,1]],[[7012,2823],[70,-23],[288,102],[81,12],[68,-5],[46,13],[72,-45],[36,-44],[54,-90],[33,-89],[-80,104],[-52,42],[-47,7],[-75,-7],[-66,-22],[-79,-41],[-71,-64],[-46,-13],[-85,5],[-101,40],[-194,142],[11,17],[47,14],[57,-15],[33,-40]],[[5689,4168],[3,-45],[-33,73],[6,76],[7,29],[-11,36],[23,123],[1,41],[-4,15],[-14,8],[-16,-10],[-23,8],[-13,35],[-17,12],[-5,14],[10,26],[19,-7],[22,57],[-7,36],[6,28],[-1,35],[6,22],[-12,31],[6,7],[11,92],[-3,26],[5,14],[-15,17],[12,22],[9,34],[-16,4],[36,26],[-22,57],[11,33],[-5,31],[5,19],[22,15],[14,-14],[13,1],[20,-53],[28,-17],[83,-203],[-5,-12]],[[5340,5698],[21,-80],[43,-119],[23,-29],[19,-41],[21,-15],[18,-91],[-120,-96],[-19,-11],[-16,8],[-8,-13],[-29,15],[-30,1],[-17,16],[-38,-7],[-93,88],[24,87],[-13,12],[23,75],[0,89],[-10,24],[28,74],[-4,24],[17,56],[22,20],[14,-18],[19,0],[20,17],[17,-16],[9,4],[59,-74]],[[6174,6353],[20,5],[12,19],[20,8],[13,2],[-1,-32],[50,-15],[-51,-56],[-27,-55],[-29,-97],[-34,-65],[-20,-22],[-31,0],[-29,-30],[-86,-160],[-10,-1],[4,7],[-4,3],[0,16],[-21,-7],[-22,39],[-5,-6],[6,14],[-7,29],[6,49],[-12,68]],[[6057,6290],[53,19],[9,-4]],[[6318,2409],[-65,-131],[-61,-140],[-57,-95],[-138,-110],[-99,-42],[-88,-49],[-186,-129],[-40,-1],[-130,-99],[-31,15],[-18,35],[-8,43],[13,102],[-48,58],[-23,-22],[87,112],[18,89],[59,90],[88,193],[42,-52],[73,140],[91,56],[2,19],[19,34],[11,144],[14,8],[2,30],[10,-1],[3,174],[27,198],[57,-262],[5,-102],[22,-70],[6,-38],[-10,-24],[13,-72],[24,-34],[-82,-17],[135,25],[45,-10],[32,25],[134,24],[27,52],[13,-10],[3,-47],[14,-19],[-14,-50],[9,-40]],[[6060,6287],[31,5],[24,32],[-80,-177],[-4,-49],[-13,-18],[-24,5],[-11,-9],[-32,-92],[-26,-155],[-49,87],[47,138],[21,30],[-4,-9],[11,4],[81,173],[28,35]],[[5295,4943],[-46,19],[-139,84],[-73,145],[-108,105],[-37,65],[6,-5],[31,33],[32,50],[25,14],[19,42],[53,-153],[10,-51],[22,-43],[16,-15],[17,1],[20,-20],[27,-62],[11,-4],[70,-116],[19,-10],[13,-22],[12,-57]],[[3478,1950],[-23,-5],[-208,277],[-36,79],[7,25],[168,268],[32,77],[126,236],[150,-335],[50,-89],[171,-265],[-238,-180],[-88,-31],[-51,-34],[-60,-23]],[[7833,2933],[74,80],[111,32],[51,38],[70,86],[82,164],[34,134],[-4,100],[75,74],[99,256],[97,178],[9,0],[-8,-258],[25,-59],[-21,-81],[-3,-95],[-12,-15],[-5,-44],[13,-56],[-2,-97],[-15,-26],[-11,21],[-73,-7],[-88,-201],[-134,-229],[-74,-94],[-50,-109],[-127,-147],[-58,-2],[-42,14],[-74,46],[39,117],[24,138],[-2,42]],[[4425,8148],[-27,87],[9,39],[-20,137],[-10,33],[9,23],[3,31],[-3,2],[9,18],[62,17],[21,55],[141,186],[118,89],[26,5],[7,-213],[-15,-172],[-58,-303],[-18,13],[-28,-27],[-49,50],[-59,-16],[-25,16],[-65,-55],[-28,-15]],[[9021,8874],[-62,-3],[-50,58],[-116,46],[-68,-14],[-110,-42],[-186,7],[-74,-22],[-79,1],[-141,-49],[-72,42],[-57,19],[-115,-4],[-40,74],[-7,27],[120,22],[86,41],[161,130],[109,57],[36,57],[64,43],[118,38],[97,166],[51,63],[112,20],[131,-44],[172,-28],[42,1],[44,18],[41,35],[0,1],[100,73],[8,-73],[-26,-104],[-5,-62],[-18,-102],[-26,-215],[-44,-54],[-112,-179],[-84,-44]],[[4265,4907],[-2,-65],[5,-48],[39,-94],[34,-42],[33,41],[14,-14],[21,-70],[4,-119],[35,-113],[7,-39],[34,-54],[11,-28],[8,-63],[-5,-65],[18,-70],[85,-203],[213,-374],[15,-79],[38,-54],[-7,-33],[-35,-18],[-3,-18],[7,-35],[-13,-77],[-17,-39],[-64,-20],[-69,-66],[-63,-88],[-21,-104],[21,-24],[-6,-32],[-22,3],[-11,-32],[32,-54],[1,-25],[-21,-26],[-21,-49],[-29,5],[-101,-137],[-79,-63],[-37,-16],[-70,2],[-100,-33],[-52,-45],[-58,-67],[-51,-41],[-64,-2],[-28,-16],[-164,274],[-47,92],[-216,537],[-61,241],[61,135],[17,53],[11,66],[0,64],[-12,117],[-25,126],[-19,225],[3,312],[16,202],[14,76],[20,65],[50,130],[31,65],[56,68],[46,-36],[108,-30],[1,-7],[22,10],[17,22],[64,122],[12,13],[111,56],[33,-21],[0,-11],[44,-37],[36,-54],[4,13],[107,-96],[35,-66],[-1,-23]],[[5258,7964],[120,-302],[30,-89],[14,-101],[3,-132],[-42,129],[-7,75],[-33,129],[-46,39],[-43,98],[-17,19],[-8,38],[-20,43],[-11,54],[14,65],[31,64],[12,-28],[2,-57],[-4,-18],[5,-26]],[[5395,7466],[5,-28],[20,-19],[13,-27],[-18,-92],[-24,-69],[-16,-114],[-15,-114],[4,-81],[-2,-47],[-13,-53],[0,-32],[-9,-19],[-8,-43],[-7,-130],[-38,-66],[-22,-6],[-19,-29],[-33,-86],[-33,-38],[-29,-197],[-15,-39],[-43,15],[-13,17],[-47,155],[-32,272],[-7,28],[31,275],[-16,102],[0,99],[-19,145],[-14,36],[-3,97],[5,51],[-4,-5],[6,43],[113,167],[97,84],[29,-2],[36,-24],[18,0],[10,-28],[63,-59],[49,-139]],[[4074,5154],[24,-130],[-10,11],[-5,-12],[-35,57],[-43,41],[0,11],[-33,24],[-112,-45],[-12,-12],[-66,-116],[-17,-20],[-23,-7],[-1,7],[-107,40],[-46,41],[72,67],[29,44],[8,22],[1,64],[52,36],[14,21],[9,29],[-15,-4],[-4,42],[83,50],[25,-8],[34,-27],[64,-19],[40,-27],[26,-35],[20,-43],[28,-102]],[[6239,2241],[190,105]],[[6685,2368],[127,-13]],[[6812,2355],[26,-59],[-1,-38],[4,-10],[-8,8],[-6,-48],[11,-62],[17,-30],[23,-153],[11,-166],[93,-168],[74,-69],[110,-70],[342,-89],[116,45],[120,-65],[16,-17],[-98,-66],[-273,-127],[-59,-39],[-123,-28],[-144,-101],[-274,67],[-105,-30],[-146,19],[-7,-12],[-300,34],[-71,38],[-32,-13],[-41,33],[-42,-2],[-55,39],[-69,4],[-127,-53],[-64,-6],[-65,36],[-117,-59],[-54,56],[-129,77],[-36,-1],[-76,33],[-24,47],[39,32],[97,27],[52,39],[78,0],[91,87],[61,32],[49,56],[72,43],[55,19],[24,40],[21,-10],[42,124],[74,125],[73,45],[2,29],[-13,43],[12,4],[0,21],[19,-12],[70,205],[53,-39],[26,-4]],[[6119,4147],[29,-39],[-19,-24],[-8,4],[-37,-18],[-68,-59],[-10,-23],[-40,-24],[-44,12],[-7,69],[-9,21],[-28,5],[-24,40],[-8,-40],[-18,-27],[-14,-4],[-28,173],[-1,56],[76,34],[56,-11],[9,-16],[13,-48],[16,-15],[21,22],[43,-11],[77,-32],[15,-20],[8,-25]],[[7259,1867],[179,-88],[106,-29],[86,-37],[167,-42],[71,-46],[67,-65],[11,-57],[42,-88],[17,-60],[-91,-65],[-40,-112],[19,-50],[108,-87],[-117,-33],[-127,8],[-100,44],[-84,21],[-83,-20],[-67,-79],[-318,-72],[-47,83],[-46,23],[-249,61],[197,44],[86,32],[61,34],[43,36],[253,-69],[111,67],[162,65],[-56,31],[-23,34],[34,43],[-11,17],[-79,-32],[-67,2],[-177,-30],[-239,46],[-78,48],[-72,51],[-26,41],[-71,42],[-30,55],[-70,161],[-13,80],[1,71],[14,42],[19,33],[-26,97],[-16,35],[-36,-6],[-51,81],[-55,-5],[-32,-44],[-22,-18],[-65,6],[-14,15],[-8,71],[-12,15],[-42,-15],[-38,-29],[-31,-32],[-25,-47],[-35,-8],[-72,68],[-17,51],[171,140],[149,164],[142,58],[94,-1],[87,-28],[29,-44],[27,-81],[25,-52],[58,-97],[63,-125],[36,-99],[45,-75],[198,-149]]],"bbox":[-180,-90,180,64.287954],"transform":{"scale":[0.036003600360036005,0.015430338433843385],"translate":[-180,-90]}}